fikra/__init__.py
fikra/core.py
fikra-0.2.0.dist-info/METADATA
fikra-0.2.0.dist-info/WHEEL
fikra-0.2.0.dist-info/top_level.txt
fikra-0.2.0.dist-info/RECORD
