Metadata-Version: 2.4
Name: fikra
Version: 0.2.0
Summary: The Lacesse Edge AI SDK. Offline reasoning.
Author: Lacesse Ventures
Author-email: jbm@lacesse.app
Requires-Python: >=3.8
Requires-Dist: llama-cpp-python>=0.2.23
Requires-Dist: huggingface_hub>=0.19.0
Dynamic: author
Dynamic: author-email
Dynamic: requires-dist
Dynamic: requires-python
Dynamic: summary
